[
  {
    "ts_code": "000586.SZ",
    "name": "汇源通信",
    "fullname": "四川汇源光通信股份有限公司",
    "industry": "通信设备",
    "area": "四川",
    "province": "四川",
    "city": "成都市",
    "employees": "471",
    "reg_capital": "19344.0",
    "setup_date": "19940304",
    "list_date": "19951220",
    "main_business": "主要业务:进出口,光缆及相关产品,通讯设备.",
    "business_scope": "一般项目:光纤制造;光纤销售;光缆制造;光缆销售;光电子器件制造;光电子器件销售;汽车零部件研发;汽车零部件及配件制造;机械电气设备制造;机械电气设备销售;电子元器件制造;电力电子元器件销售;物联网设备制造;物联网设备销售;光学仪器制造;光学仪器销售;照明器具制造;照明器具销售;智能车载设备制造;智能车载设备销售;工业自动控制系统装置制造;工业自动控制系统装置销售;工业控制计算机及系统制造;工业控制计算机及系统销售;集成电路设计;集成电路芯片设计及服务;集成电路芯片及产品销售;软件开发;软件销售;通信设备制造;通信设备销售;货物进出口;销售代理;技术服务,技术开发,技术咨询,技术交流,技术转让,技术推广.(除依法须经批准的项目外,凭营业执照依法自主开展经营活动)"
  },
  {
    "ts_code": "000589.SZ",
    "name": "贵州轮胎",
    "fullname": "贵州轮胎股份有限公司",
    "industry": "汽车配件",
    "area": "贵州",
    "province": "贵州",
    "city": "贵阳市",
    "employees": "6627",
    "reg_capital": "155462.4504",
    "setup_date": "19960129",
    "list_date": "19960308",
    "main_business": "主要业务:“前进牌”轮胎的生产与销售.主要产品:斜交轮胎和子午线轮胎.",
    "business_scope": "法律,法规,国务院决定规定禁止的不得经营;法律,法规,国务院决定规定应当许可(审批)的,经审批机关批准后凭许可(审批)文件经营;法律,法规,国务院决定规定无需许可(审批)的,市场主体自主选择经营.(轮胎制造和销售;轮胎翻新和销售;橡胶制品制造和销售;水电,蒸汽,混炼胶及其他附属品的制造和销售;经营各类商品及技术进出口业务(国家禁止类除外),开展对外合作生产及“三来一补”业务;仓储;物流运输.)"
  },
  {
    "ts_code": "000590.SZ",
    "name": "古汉医药",
    "fullname": "古汉医药集团股份公司",
    "industry": "中成药",
    "area": "湖南",
    "province": "湖南",
    "city": "衡阳市",
    "employees": "1064",
    "reg_capital": "23947.1267",
    "setup_date": "19931112",
    "list_date": "19960119",
    "main_business": "主要产品:古汉养生精,克林霉素磷酸酯,人血白蛋白.",
    "business_scope": "保健食品,消毒用品,消毒器械,卫生防护用品的销售;酒类经营,化妆品批发,化妆品零售,预包装食品散装食品,饮料批发兼零售;特殊医学用途配方食品销售;日用化学产品销售日用百货销售;药品互联网信息服务;婴幼儿配方乳粉及其他婴幼儿配方食品销售,国内贸易代理,货物进出口:技术进出口:普通货物仓储运输服务:健康管理,健康咨询服务(不含诊疗服务):养生保健服务(非医疗):技术服务,技术开发,技术咨询,技术交流,技术转让,技术推广,广告服务:广告制作服务,发布服务:广告设计,商品信息咨询服务:企业形象策划,品牌策划咨询服务;企业管理咨询服务,市场营销策划服务;中医药推广;中医药文化推广;组织文化艺术交流活动,会议及展览服务."
  },
  {
    "ts_code": "000591.SZ",
    "name": "太阳能",
    "fullname": "中节能太阳能股份有限公司",
    "industry": "新型电力",
    "area": "重庆",
    "province": "重庆",
    "city": "重庆市",
    "employees": "1781",
    "reg_capital": "392580.0512",
    "setup_date": "19930412",
    "list_date": "19960208",
    "main_business": "主营业务:以太阳能光伏电站的投资运营为主.",
    "business_scope": "太阳能发电及电力储备;太阳能技术及相关配套产品研发,应用,转让及销售;太阳能应用技术咨询服务;太阳能发电项目开发,设计,组织建设,维护与经营管理;太阳能发电电子系统设备研发,制造,销售;储能技术设备和材料的研发,制造,销售;光伏农业,光伏林业,光伏牧业,光伏渔业项目开发,组织建设与经营管理;分布式光伏项目开发,组织建设及经营管理;能源智能化经营管理;货物及技术进出口业务;物业管理."
  },
  {
    "ts_code": "000592.SZ",
    "name": "平潭发展",
    "fullname": "中福海峡(平潭)发展股份有限公司",
    "industry": "林业",
    "area": "福建",
    "province": "福建",
    "city": "福州市",
    "employees": "1067",
    "reg_capital": "193178.0892",
    "setup_date": "19930908",
    "list_date": "19960327",
    "main_business": "主要业务:造林营林,林木产品加工与销售,以烟草化肥销售为主的农资贸易业务与平潭综合实验区开放开发的有关业务.",
    "business_scope": "一般项目:人造板制造;人造板销售;森林经营和管护;人工造林;森林改培;林产品采集;树木种植经营;林业专业及辅助性活动;进出口代理;货物进出口;规划设计管理;非食用农产品初加工;木材加工;林业产品销售;木材收购;非居住房地产租赁;住房租赁;物业管理;普通货物仓储服务(不含危险化学品等需许可审批的项目);国内货物运输代理;以自有资金从事投资活动;技术服务,技术开发,技术咨询,技术交流,技术转让,技术推广;化肥销售;肥料销售;新型建筑材料制造(不含危险化学品);建筑砌块制造;建筑材料销售;建筑用木料及木材组件加工;园林绿化工程施工;农副产品销售;畜牧渔业饲料销售;饲料原料销售;纸制造;纸浆制造;纸浆销售.(除依法须经批准的项目外,凭营业执照依法自主开展经营活动)许可项目:木材采运;住宅室内装饰装修;建设工程施工.(依法须经批准的项目,经相关部门批准后方可开展经营活动,具体经营项目以相关部门批准文件或许可证件为准)"
  },
  {
    "ts_code": "000593.SZ",
    "name": "德龙汇能",
    "fullname": "德龙汇能集团股份有限公司",
    "industry": "供气供热",
    "area": "四川",
    "province": "四川",
    "city": "成都市",
    "employees": "951",
    "reg_capital": "35863.1009",
    "setup_date": "19940101",
    "list_date": "19960312",
    "main_business": "主要业务:城市燃气业务,LNG业务和分布式能源业务.",
    "business_scope": "城市管道燃气的开发及投资,燃气购销,货物进出口业务,燃气器材的购销和维修,天然气利用工程建设与经营和相关专业技术服务;仓储服务,实业投资;高新科技技术及产品的开发;房地产项目的投资及开发.(以上项目涉及许可证的凭取得相关许可证后方可经营,国家法律,法规限制和禁止的不得经营.)"
  },
  {
    "ts_code": "000595.SZ",
    "name": "*ST宝实",
    "fullname": "宁夏国运新能源股份有限公司",
    "industry": "新型电力",
    "area": "宁夏",
    "province": "宁夏",
    "city": "银川市",
    "employees": "729",
    "reg_capital": "113865.6366",
    "setup_date": "19960413",
    "list_date": "19960419",
    "main_business": "主要业务:各类滚动轴承的生产和销售.",
    "business_scope": "许可项目:发电业务,输电业务,供(配)电业务(依法须经批准的项目,经相关部门批准后方可开展经营活动).一般项目:风力发电技术服务;太阳能发电技术服务;储能技术服务;技术服务,技术开发,技术咨询,技术交流,技术转让,技术推广(除许可业务外,可自主依法经营法律法规非禁止或限制的项目)."
  },
  {
    "ts_code": "000596.SZ",
    "name": "古井贡酒",
    "fullname": "安徽古井贡酒股份有限公司",
    "industry": "白酒",
    "area": "安徽",
    "province": "安徽",
    "city": "亳州市",
    "employees": "13453",
    "reg_capital": "52860.0",
    "setup_date": "19990305",
    "list_date": "19960927",
    "main_business": "主要产品:白酒.",
    "business_scope": "粮食收购(凭许可证经营),生产白酒,酿酒设备,包装材料,玻璃瓶,酒精,油脂(限于酒精生产的副产品),高新技术开发,生物技术开发,农副产品深加工,销售自产产品."
  },
  {
    "ts_code": "000597.SZ",
    "name": "东北制药",
    "fullname": "东北制药集团股份有限公司",
    "industry": "化学制药",
    "area": "辽宁",
    "province": "辽宁",
    "city": "沈阳市",
    "employees": "5727",
    "reg_capital": "142708.8265",
    "setup_date": "19930610",
    "list_date": "19960523",
    "main_business": "主要业务:制造和销售化学原料药品,制剂药品.主要产品:原料药(磷霉素钠,氯霉素,磺胺嘧啶,脑复康等);成药制剂(注射用磷霉素钠,注射用头孢噻肟钠,整肠生,消刻等)",
    "business_scope": "一般项目:基础化学原料制造(不含危险化学品等许可类化学品的制造);食品添加剂销售;饲料添加剂销售;消毒剂销售(不含危险化学品);专用化学产品制造(不含危险化学品);专用化学产品销售(不含危险化学品);化工产品生产(不含许可类化工产品);化工产品销售(不含许可类化工产品);化妆品零售;化妆品批发;技术服务,技术开发,技术咨询,技术交流,技术转让,技术推广;环保咨询服务;医学研究和试验发展;污水处理及其再生利用;金属材料销售;非居住房地产租赁;机械设备租赁;小微型客车租赁经营服务;办公设备租赁服务;特种设备出租;医用包装材料制造;包装材料及制品销售;货物进出口;技术进出口;食品进出口;食品销售(仅销售预包装食品);食品互联网销售(仅销售预包装食品);互联网销售(除销售需要许可的商品).(除依法须经批准的项目外,凭营业执照依法自主开展经营活动)许可项目:药品生产;药品进出口;食品添加剂生产;药品批发;药品零售;饲料添加剂生产;危险化学品生产;危险化学品经营;消毒剂生产(不含危险化学品);化妆品生产;食品生产.(依法须经批准的项目,经相关部门批准后方可开展经营活动,具体经营项目以相关部门批准文件或许可证件为准)."
  },
  {
    "ts_code": "000598.SZ",
    "name": "兴蓉环境",
    "fullname": "成都市兴蓉环境股份有限公司",
    "industry": "水务",
    "area": "四川",
    "province": "四川",
    "city": "成都市",
    "employees": "5325",
    "reg_capital": "298400.8721",
    "setup_date": "19960526",
    "list_date": "19960529",
    "main_business": "主营业务:污水处理",
    "business_scope": "经依法登记,公司经营范围:自来水,污水处理,污泥处理,环保项目的投资,设计,建设,运营管理,技术开发,技术咨询,技术服务;水务,环保相关设备及物资的销售和维修;高新技术项目的开发;对外投资及资本运营,投资管理及咨询(不得从事非法集资,吸收公众资金等金融活动);货物进出口,技术进出口.(依法须经批准的项目,经相关部门批准后方可开展经营活动)."
  }
]