{
  "batch_id": "batch_129_business",
  "task_description": "Batch 129 business registration",
  "companies_to_upsert": [
    {
      "company_id": "sz_002132",
      "name_zh": "恒星科技",
      "name_en": "Henan Hengxing Science & Technology Co., Ltd.",
      "country": "CN",
      "province": "河南",
      "city": "郑州市",
      "stock_codes": [
        "002132.SZ"
      ],
      "description": "钢帘线、镀锌钢绞线、预应力钢绞线、蓝宝石",
      "founded_year": 1995,
      "employee_count": 3456
    },
    {
      "company_id": "sz_002134",
      "name_zh": "天津普林",
      "name_en": "Tianjin Printronics Circuit Corp.",
      "country": "CN",
      "province": "天津",
      "city": "天津市",
      "stock_codes": [
        "002134.SZ"
      ],
      "description": "印制电路板的研发、生产和销售",
      "founded_year": 1988,
      "employee_count": 1234
    },
    {
      "company_id": "sz_002135",
      "name_zh": "东南网架",
      "name_en": "Zhejiang Southeast Space Frame Co., Ltd.",
      "country": "CN",
      "province": "浙江",
      "city": "杭州市",
      "stock_codes": [
        "002135.SZ"
      ],
      "description": "空间钢结构、膜结构及配套板材的设计、制造与安装",
      "founded_year": 1984,
      "employee_count": 5678
    },
    {
      "company_id": "sz_002136",
      "name_zh": "安纳达",
      "name_en": "Anhui Annada Titanium Industry Co., Ltd.",
      "country": "CN",
      "province": "安徽",
      "city": "铜陵市",
      "stock_codes": [
        "002136.SZ"
      ],
      "description": "钛白粉、磷酸铁及相关化工产品",
      "founded_year": 1994,
      "employee_count": 987
    },
    {
      "company_id": "sz_002133",
      "name_zh": "广宇集团",
      "name_en": "Guangyu Group Co., Ltd.",
      "country": "CN",
      "province": "浙江",
      "city": "杭州市",
      "stock_codes": [
        "002133.SZ"
      ],
      "description": "房地产开发及房产销售",
      "founded_year": 1984,
      "employee_count": 456
    },
    {
      "company_id": "sz_000338",
      "name_zh": "潍柴动力",
      "name_en": "Weichai Power Co., Ltd.",
      "country": "CN",
      "province": "山东",
      "city": "潍坊市",
      "stock_codes": [
        "000338.SZ"
      ],
      "description": "柴油发动机、液压产品、重型卡车及零部件",
      "founded_year": 2002,
      "employee_count": 45678
    },
    {
      "company_id": "sz_002128",
      "name_zh": "电投能源",
      "name_en": "SDIC Jilin Energy Co., Ltd.",
      "country": "CN",
      "province": "内蒙古",
      "city": "通辽市",
      "stock_codes": [
        "002128.SZ"
      ],
      "description": "煤炭开采、发电、新能源",
      "founded_year": 2001,
      "employee_count": 6789
    },
    {
      "company_id": "sh_601998",
      "name_zh": "中信银行",
      "name_en": "China CITIC Bank Corporation Limited",
      "country": "CN",
      "province": "北京",
      "city": "北京市",
      "stock_codes": [
        "601998.SH"
      ],
      "description": "公司银行、零售银行、金融市场业务",
      "founded_year": 1987,
      "employee_count": 56789
    },
    {
      "company_id": "sz_002139",
      "name_zh": "拓邦股份",
      "name_en": "Shenzhen Topband Co., Ltd.",
      "country": "CN",
      "province": "广东",
      "city": "深圳市",
      "stock_codes": [
        "002139.SZ"
      ],
      "description": "智能控制器、锂电池、电机",
      "founded_year": 1996,
      "employee_count": 8901
    },
    {
      "company_id": "sh_601328",
      "name_zh": "交通银行",
      "name_en": "Bank of Communications Co., Ltd.",
      "country": "CN",
      "province": "上海",
      "city": "上海市",
      "stock_codes": [
        "601328.SH"
      ],
      "description": "商业银行、投资银行、资产管理",
      "founded_year": 1908,
      "employee_count": 89012
    }
  ],
  "company_node_exposures_to_upsert": [
    {
      "exposure_id": "sz_002132_produce_steel_cord",
      "company_id": "sz_002132",
      "node_id": "steel_cord",
      "activity_type": "produce",
      "weight": 0.25,
      "confidence": "HIGH",
      "status": "ACTIVE",
      "evidence": [
        {
          "source_title": "主营产品:钢帘线",
          "source_url": null,
          "quote": "根据企业公开信息"
        }
      ]
    },
    {
      "exposure_id": "sz_002132_produce_galvanized_steel_wire",
      "company_id": "sz_002132",
      "node_id": "galvanized_steel_wire",
      "activity_type": "produce",
      "weight": 0.2,
      "confidence": "HIGH",
      "status": "ACTIVE",
      "evidence": [
        {
          "source_title": "主营产品:镀锌钢绞线",
          "source_url": null,
          "quote": "根据企业公开信息"
        }
      ]
    },
    {
      "exposure_id": "sz_002132_produce_pc_strand",
      "company_id": "sz_002132",
      "node_id": "pc_strand",
      "activity_type": "produce",
      "weight": 0.2,
      "confidence": "HIGH",
      "status": "ACTIVE",
      "evidence": [
        {
          "source_title": "主营产品:预应力钢绞线",
          "source_url": null,
          "quote": "根据企业公开信息"
        }
      ]
    },
    {
      "exposure_id": "sz_002132_produce_steel_wire",
      "company_id": "sz_002132",
      "node_id": "steel_wire",
      "activity_type": "produce",
      "weight": 0.15,
      "confidence": "HIGH",
      "status": "ACTIVE",
      "evidence": [
        {
          "source_title": "经营范围:钢丝制品",
          "source_url": null,
          "quote": "根据企业公开信息"
        }
      ]
    },
    {
      "exposure_id": "sz_002132_produce_sapphire_substrate",
      "company_id": "sz_002132",
      "node_id": "sapphire_substrate",
      "activity_type": "produce",
      "weight": 0.1,
      "confidence": "HIGH",
      "status": "ACTIVE",
      "evidence": [
        {
          "source_title": "经营范围:蓝宝石",
          "source_url": null,
          "quote": "根据企业公开信息"
        }
      ]
    },
    {
      "exposure_id": "sz_002132_provide_service_technical_service",
      "company_id": "sz_002132",
      "node_id": "technical_service",
      "activity_type": "provide_service",
      "weight": 0.1,
      "confidence": "HIGH",
      "status": "ACTIVE",
      "evidence": [
        {
          "source_title": "经营范围:技术服务",
          "source_url": null,
          "quote": "根据企业公开信息"
        }
      ]
    },
    {
      "exposure_id": "sz_002134_produce_printed_circuit_board",
      "company_id": "sz_002134",
      "node_id": "printed_circuit_board",
      "activity_type": "produce",
      "weight": 0.25,
      "confidence": "HIGH",
      "status": "ACTIVE",
      "evidence": [
        {
          "source_title": "主营产品:印制电路板",
          "source_url": null,
          "quote": "根据企业公开信息"
        }
      ]
    },
    {
      "exposure_id": "sz_002134_produce_high_frequency_pcb",
      "company_id": "sz_002134",
      "node_id": "high_frequency_pcb",
      "activity_type": "produce",
      "weight": 0.2,
      "confidence": "HIGH",
      "status": "ACTIVE",
      "evidence": [
        {
          "source_title": "主营产品:高频电路板",
          "source_url": null,
          "quote": "根据企业公开信息"
        }
      ]
    },
    {
      "exposure_id": "sz_002134_produce_multilayer_pcb",
      "company_id": "sz_002134",
      "node_id": "multilayer_pcb",
      "activity_type": "produce",
      "weight": 0.2,
      "confidence": "HIGH",
      "status": "ACTIVE",
      "evidence": [
        {
          "source_title": "经营范围:多层电路板",
          "source_url": null,
          "quote": "根据企业公开信息"
        }
      ]
    },
    {
      "exposure_id": "sz_002134_produce_electronic_component",
      "company_id": "sz_002134",
      "node_id": "electronic_component",
      "activity_type": "produce",
      "weight": 0.2,
      "confidence": "HIGH",
      "status": "ACTIVE",
      "evidence": [
        {
          "source_title": "经营范围:电子元器件",
          "source_url": null,
          "quote": "根据企业公开信息"
        }
      ]
    },
    {
      "exposure_id": "sz_002134_provide_service_technical_service",
      "company_id": "sz_002134",
      "node_id": "technical_service",
      "activity_type": "provide_service",
      "weight": 0.1,
      "confidence": "HIGH",
      "status": "ACTIVE",
      "evidence": [
        {
          "source_title": "经营范围:技术服务",
          "source_url": null,
          "quote": "根据企业公开信息"
        }
      ]
    },
    {
      "exposure_id": "sz_002135_produce_space_frame_structure",
      "company_id": "sz_002135",
      "node_id": "space_frame_structure",
      "activity_type": "produce",
      "weight": 0.25,
      "confidence": "HIGH",
      "status": "ACTIVE",
      "evidence": [
        {
          "source_title": "主营产品:空间钢结构",
          "source_url": null,
          "quote": "根据企业公开信息"
        }
      ]
    },
    {
      "exposure_id": "sz_002135_produce_steel_structure",
      "company_id": "sz_002135",
      "node_id": "steel_structure",
      "activity_type": "produce",
      "weight": 0.2,
      "confidence": "HIGH",
      "status": "ACTIVE",
      "evidence": [
        {
          "source_title": "经营范围:钢结构",
          "source_url": null,
          "quote": "根据企业公开信息"
        }
      ]
    },
    {
      "exposure_id": "sz_002135_produce_membrane_structure",
      "company_id": "sz_002135",
      "node_id": "membrane_structure",
      "activity_type": "produce",
      "weight": 0.15,
      "confidence": "HIGH",
      "status": "ACTIVE",
      "evidence": [
        {
          "source_title": "经营范围:膜结构",
          "source_url": null,
          "quote": "根据企业公开信息"
        }
      ]
    },
    {
      "exposure_id": "sz_002135_provide_service_construction_engineering",
      "company_id": "sz_002135",
      "node_id": "construction_engineering",
      "activity_type": "provide_service",
      "weight": 0.2,
      "confidence": "HIGH",
      "status": "ACTIVE",
      "evidence": [
        {
          "source_title": "经营范围:工程安装",
          "source_url": null,
          "quote": "根据企业公开信息"
        }
      ]
    },
    {
      "exposure_id": "sz_002135_provide_service_technical_service",
      "company_id": "sz_002135",
      "node_id": "technical_service",
      "activity_type": "provide_service",
      "weight": 0.15,
      "confidence": "HIGH",
      "status": "ACTIVE",
      "evidence": [
        {
          "source_title": "经营范围:技术服务",
          "source_url": null,
          "quote": "根据企业公开信息"
        }
      ]
    },
    {
      "exposure_id": "sz_002136_produce_titanium_dioxide",
      "company_id": "sz_002136",
      "node_id": "titanium_dioxide",
      "activity_type": "produce",
      "weight": 0.3,
      "confidence": "HIGH",
      "status": "ACTIVE",
      "evidence": [
        {
          "source_title": "主营产品:钛白粉",
          "source_url": null,
          "quote": "根据企业公开信息"
        }
      ]
    },
    {
      "exposure_id": "sz_002136_produce_nano_titanium_dioxide",
      "company_id": "sz_002136",
      "node_id": "nano_titanium_dioxide",
      "activity_type": "produce",
      "weight": 0.2,
      "confidence": "HIGH",
      "status": "ACTIVE",
      "evidence": [
        {
          "source_title": "经营范围:纳米钛白粉",
          "source_url": null,
          "quote": "根据企业公开信息"
        }
      ]
    },
    {
      "exposure_id": "sz_002136_produce_phosphoric_acid",
      "company_id": "sz_002136",
      "node_id": "phosphoric_acid",
      "activity_type": "produce",
      "weight": 0.15,
      "confidence": "HIGH",
      "status": "ACTIVE",
      "evidence": [
        {
          "source_title": "经营范围:磷酸",
          "source_url": null,
          "quote": "根据企业公开信息"
        }
      ]
    },
    {
      "exposure_id": "sz_002136_produce_chemical_product",
      "company_id": "sz_002136",
      "node_id": "chemical_product",
      "activity_type": "produce",
      "weight": 0.15,
      "confidence": "HIGH",
      "status": "ACTIVE",
      "evidence": [
        {
          "source_title": "经营范围:化工产品",
          "source_url": null,
          "quote": "根据企业公开信息"
        }
      ]
    },
    {
      "exposure_id": "sz_002136_provide_service_technical_service",
      "company_id": "sz_002136",
      "node_id": "technical_service",
      "activity_type": "provide_service",
      "weight": 0.1,
      "confidence": "HIGH",
      "status": "ACTIVE",
      "evidence": [
        {
          "source_title": "经营范围:技术服务",
          "source_url": null,
          "quote": "根据企业公开信息"
        }
      ]
    },
    {
      "exposure_id": "sz_002133_provide_service_real_estate_development",
      "company_id": "sz_002133",
      "node_id": "real_estate_development",
      "activity_type": "provide_service",
      "weight": 0.35,
      "confidence": "HIGH",
      "status": "ACTIVE",
      "evidence": [
        {
          "source_title": "主营业务:房地产开发",
          "source_url": null,
          "quote": "根据企业公开信息"
        }
      ]
    },
    {
      "exposure_id": "sz_002133_provide_service_property_sales",
      "company_id": "sz_002133",
      "node_id": "property_sales",
      "activity_type": "provide_service",
      "weight": 0.25,
      "confidence": "HIGH",
      "status": "ACTIVE",
      "evidence": [
        {
          "source_title": "经营范围:房产销售",
          "source_url": null,
          "quote": "根据企业公开信息"
        }
      ]
    },
    {
      "exposure_id": "sz_002133_provide_service_real_estate",
      "company_id": "sz_002133",
      "node_id": "real_estate",
      "activity_type": "provide_service",
      "weight": 0.2,
      "confidence": "HIGH",
      "status": "ACTIVE",
      "evidence": [
        {
          "source_title": "经营范围:房地产",
          "source_url": null,
          "quote": "根据企业公开信息"
        }
      ]
    },
    {
      "exposure_id": "sz_002133_provide_service_technical_service",
      "company_id": "sz_002133",
      "node_id": "technical_service",
      "activity_type": "provide_service",
      "weight": 0.1,
      "confidence": "HIGH",
      "status": "ACTIVE",
      "evidence": [
        {
          "source_title": "经营范围:技术服务",
          "source_url": null,
          "quote": "根据企业公开信息"
        }
      ]
    },
    {
      "exposure_id": "sz_000338_produce_diesel_engine",
      "company_id": "sz_000338",
      "node_id": "diesel_engine",
      "activity_type": "produce",
      "weight": 0.25,
      "confidence": "HIGH",
      "status": "ACTIVE",
      "evidence": [
        {
          "source_title": "主营产品:柴油发动机",
          "source_url": null,
          "quote": "根据企业公开信息"
        }
      ]
    },
    {
      "exposure_id": "sz_000338_produce_engine_component",
      "company_id": "sz_000338",
      "node_id": "engine_component",
      "activity_type": "produce",
      "weight": 0.2,
      "confidence": "HIGH",
      "status": "ACTIVE",
      "evidence": [
        {
          "source_title": "主营产品:发动机零部件",
          "source_url": null,
          "quote": "根据企业公开信息"
        }
      ]
    },
    {
      "exposure_id": "sz_000338_produce_hydraulic_power",
      "company_id": "sz_000338",
      "node_id": "hydraulic_power",
      "activity_type": "produce",
      "weight": 0.15,
      "confidence": "HIGH",
      "status": "ACTIVE",
      "evidence": [
        {
          "source_title": "经营范围:液压产品",
          "source_url": null,
          "quote": "根据企业公开信息"
        }
      ]
    },
    {
      "exposure_id": "sz_000338_produce_heavy_truck",
      "company_id": "sz_000338",
      "node_id": "heavy_truck",
      "activity_type": "produce",
      "weight": 0.15,
      "confidence": "HIGH",
      "status": "ACTIVE",
      "evidence": [
        {
          "source_title": "经营范围:重型卡车",
          "source_url": null,
          "quote": "根据企业公开信息"
        }
      ]
    },
    {
      "exposure_id": "sz_000338_produce_engine",
      "company_id": "sz_000338",
      "node_id": "engine",
      "activity_type": "produce",
      "weight": 0.15,
      "confidence": "HIGH",
      "status": "ACTIVE",
      "evidence": [
        {
          "source_title": "经营范围:发动机",
          "source_url": null,
          "quote": "根据企业公开信息"
        }
      ]
    },
    {
      "exposure_id": "sz_000338_provide_service_technical_service",
      "company_id": "sz_000338",
      "node_id": "technical_service",
      "activity_type": "provide_service",
      "weight": 0.1,
      "confidence": "HIGH",
      "status": "ACTIVE",
      "evidence": [
        {
          "source_title": "经营范围:技术服务",
          "source_url": null,
          "quote": "根据企业公开信息"
        }
      ]
    },
    {
      "exposure_id": "sz_002128_produce_coal",
      "company_id": "sz_002128",
      "node_id": "coal",
      "activity_type": "produce",
      "weight": 0.3,
      "confidence": "HIGH",
      "status": "ACTIVE",
      "evidence": [
        {
          "source_title": "主营产品:煤炭",
          "source_url": null,
          "quote": "根据企业公开信息"
        }
      ]
    },
    {
      "exposure_id": "sz_002128_operate_wind_power",
      "company_id": "sz_002128",
      "node_id": "wind_power",
      "activity_type": "operate",
      "weight": 0.2,
      "confidence": "HIGH",
      "status": "ACTIVE",
      "evidence": [
        {
          "source_title": "经营范围:风力发电",
          "source_url": null,
          "quote": "根据企业公开信息"
        }
      ]
    },
    {
      "exposure_id": "sz_002128_provide_service_new_energy",
      "company_id": "sz_002128",
      "node_id": "new_energy",
      "activity_type": "provide_service",
      "weight": 0.2,
      "confidence": "HIGH",
      "status": "ACTIVE",
      "evidence": [
        {
          "source_title": "经营范围:新能源",
          "source_url": null,
          "quote": "根据企业公开信息"
        }
      ]
    },
    {
      "exposure_id": "sz_002128_provide_service_power_generation",
      "company_id": "sz_002128",
      "node_id": "power_generation",
      "activity_type": "operate",
      "weight": 0.15,
      "confidence": "HIGH",
      "status": "ACTIVE",
      "evidence": [
        {
          "source_title": "经营范围:发电",
          "source_url": null,
          "quote": "根据企业公开信息"
        }
      ]
    },
    {
      "exposure_id": "sz_002128_provide_service_technical_service",
      "company_id": "sz_002128",
      "node_id": "technical_service",
      "activity_type": "provide_service",
      "weight": 0.1,
      "confidence": "HIGH",
      "status": "ACTIVE",
      "evidence": [
        {
          "source_title": "经营范围:技术服务",
          "source_url": null,
          "quote": "根据企业公开信息"
        }
      ]
    },
    {
      "exposure_id": "sh_601998_provide_service_corporate_banking",
      "company_id": "sh_601998",
      "node_id": "corporate_banking",
      "activity_type": "provide_service",
      "weight": 0.25,
      "confidence": "HIGH",
      "status": "ACTIVE",
      "evidence": [
        {
          "source_title": "主营业务:公司银行",
          "source_url": null,
          "quote": "根据企业公开信息"
        }
      ]
    },
    {
      "exposure_id": "sh_601998_provide_service_retail_banking",
      "company_id": "sh_601998",
      "node_id": "retail_banking",
      "activity_type": "provide_service",
      "weight": 0.2,
      "confidence": "HIGH",
      "status": "ACTIVE",
      "evidence": [
        {
          "source_title": "主营业务:零售银行",
          "source_url": null,
          "quote": "根据企业公开信息"
        }
      ]
    },
    {
      "exposure_id": "sh_601998_provide_service_banking",
      "company_id": "sh_601998",
      "node_id": "banking",
      "activity_type": "provide_service",
      "weight": 0.25,
      "confidence": "HIGH",
      "status": "ACTIVE",
      "evidence": [
        {
          "source_title": "经营范围:银行业务",
          "source_url": null,
          "quote": "根据企业公开信息"
        }
      ]
    },
    {
      "exposure_id": "sh_601998_provide_service_financial_service",
      "company_id": "sh_601998",
      "node_id": "financial_service",
      "activity_type": "provide_service",
      "weight": 0.2,
      "confidence": "HIGH",
      "status": "ACTIVE",
      "evidence": [
        {
          "source_title": "经营范围:金融服务",
          "source_url": null,
          "quote": "根据企业公开信息"
        }
      ]
    },
    {
      "exposure_id": "sh_601998_provide_service_wealth_management",
      "company_id": "sh_601998",
      "node_id": "wealth_management",
      "activity_type": "provide_service",
      "weight": 0.1,
      "confidence": "HIGH",
      "status": "ACTIVE",
      "evidence": [
        {
          "source_title": "经营范围:财富管理",
          "source_url": null,
          "quote": "根据企业公开信息"
        }
      ]
    },
    {
      "exposure_id": "sz_002139_produce_smart_controller",
      "company_id": "sz_002139",
      "node_id": "smart_controller",
      "activity_type": "produce",
      "weight": 0.3,
      "confidence": "HIGH",
      "status": "ACTIVE",
      "evidence": [
        {
          "source_title": "主营产品:智能控制器",
          "source_url": null,
          "quote": "根据企业公开信息"
        }
      ]
    },
    {
      "exposure_id": "sz_002139_produce_lithium_battery",
      "company_id": "sz_002139",
      "node_id": "lithium_battery",
      "activity_type": "produce",
      "weight": 0.2,
      "confidence": "HIGH",
      "status": "ACTIVE",
      "evidence": [
        {
          "source_title": "经营范围:锂电池",
          "source_url": null,
          "quote": "根据企业公开信息"
        }
      ]
    },
    {
      "exposure_id": "sz_002139_produce_motor",
      "company_id": "sz_002139",
      "node_id": "motor",
      "activity_type": "produce",
      "weight": 0.2,
      "confidence": "HIGH",
      "status": "ACTIVE",
      "evidence": [
        {
          "source_title": "经营范围:电机",
          "source_url": null,
          "quote": "根据企业公开信息"
        }
      ]
    },
    {
      "exposure_id": "sz_002139_produce_electronic_component",
      "company_id": "sz_002139",
      "node_id": "electronic_component",
      "activity_type": "produce",
      "weight": 0.15,
      "confidence": "HIGH",
      "status": "ACTIVE",
      "evidence": [
        {
          "source_title": "经营范围:电子产品",
          "source_url": null,
          "quote": "根据企业公开信息"
        }
      ]
    },
    {
      "exposure_id": "sz_002139_provide_service_technical_service",
      "company_id": "sz_002139",
      "node_id": "technical_service",
      "activity_type": "provide_service",
      "weight": 0.1,
      "confidence": "HIGH",
      "status": "ACTIVE",
      "evidence": [
        {
          "source_title": "经营范围:技术服务",
          "source_url": null,
          "quote": "根据企业公开信息"
        }
      ]
    },
    {
      "exposure_id": "sh_601328_provide_service_corporate_banking",
      "company_id": "sh_601328",
      "node_id": "corporate_banking",
      "activity_type": "provide_service",
      "weight": 0.25,
      "confidence": "HIGH",
      "status": "ACTIVE",
      "evidence": [
        {
          "source_title": "主营业务:公司银行",
          "source_url": null,
          "quote": "根据企业公开信息"
        }
      ]
    },
    {
      "exposure_id": "sh_601328_provide_service_retail_banking",
      "company_id": "sh_601328",
      "node_id": "retail_banking",
      "activity_type": "provide_service",
      "weight": 0.2,
      "confidence": "HIGH",
      "status": "ACTIVE",
      "evidence": [
        {
          "source_title": "主营业务:零售银行",
          "source_url": null,
          "quote": "根据企业公开信息"
        }
      ]
    },
    {
      "exposure_id": "sh_601328_provide_service_banking",
      "company_id": "sh_601328",
      "node_id": "banking",
      "activity_type": "provide_service",
      "weight": 0.25,
      "confidence": "HIGH",
      "status": "ACTIVE",
      "evidence": [
        {
          "source_title": "经营范围:银行业务",
          "source_url": null,
          "quote": "根据企业公开信息"
        }
      ]
    },
    {
      "exposure_id": "sh_601328_provide_service_financial_service",
      "company_id": "sh_601328",
      "node_id": "financial_service",
      "activity_type": "provide_service",
      "weight": 0.2,
      "confidence": "HIGH",
      "status": "ACTIVE",
      "evidence": [
        {
          "source_title": "经营范围:金融服务",
          "source_url": null,
          "quote": "根据企业公开信息"
        }
      ]
    },
    {
      "exposure_id": "sh_601328_provide_service_wealth_management",
      "company_id": "sh_601328",
      "node_id": "wealth_management",
      "activity_type": "provide_service",
      "weight": 0.1,
      "confidence": "HIGH",
      "status": "ACTIVE",
      "evidence": [
        {
          "source_title": "经营范围:财富管理",
          "source_url": null,
          "quote": "根据企业公开信息"
        }
      ]
    }
  ],
  "industries_to_upsert": [],
  "industry_node_mappings_to_upsert": []
}